{
  "name": "twitch-sub-defatank",
  "match": "word",
  "template": "<img src=\"//static-cdn.jtvnw.net/emoticons/v1/:image_id/1.0\" alt=\":match\" title=\":match\">",
  "icons": [
    {
      "match": "defaPalm",
      "image_id": 28186
    },
    {
      "match": "defaRekt",
      "image_id": 28185
    },
    {
      "match": "defaSub",
      "image_id": 28472
    },
    {
      "match": "defaTrain",
      "image_id": 28471
    },
    {
      "match": "defaGasm",
      "image_id": 29052
    },
    {
      "match": "defaHype",
      "image_id": 29051
    }
  ]
}