{
  "name": "twitch-sub-dehixem",
  "match": "word",
  "template": "<img src=\"//static-cdn.jtvnw.net/emoticons/v1/:image_id/1.0\" alt=\":match\" title=\":match\">",
  "icons": [
    {
      "match": "dxmRage",
      "image_id": 36026
    },
    {
      "match": "dxmLewd",
      "image_id": 36030
    },
    {
      "match": "dxmHype",
      "image_id": 36045
    },
    {
      "match": "dxmRIP",
      "image_id": 36048
    },
    {
      "match": "dxmTea",
      "image_id": 46606
    },
    {
      "match": "dxmRhoo",
      "image_id": 47028
    }
  ]
}