{
  "name": "twitch-sub-dragonseancers",
  "match": "word",
  "template": "<img src=\"//static-cdn.jtvnw.net/emoticons/v1/:image_id/1.0\" alt=\":match\" title=\":match\">",
  "icons": [
    {
      "match": "gunnarQT",
      "image_id": 19824
    },
    {
      "match": "gunnarZoom",
      "image_id": 19829
    },
    {
      "match": "gunnarEffigy",
      "image_id": 21099
    },
    {
      "match": "gunnarBands",
      "image_id": 21098
    },
    {
      "match": "gunnarUSB",
      "image_id": 37447
    },
    {
      "match": "gunnarKappa",
      "image_id": 37448
    }
  ]
}