{
  "name": "twitch-sub-freya_chan",
  "match": "word",
  "template": "<img src=\"//static-cdn.jtvnw.net/emoticons/v1/:image_id/1.0\" alt=\":match\" title=\":match\">",
  "icons": [
    {
      "match": "freyaHarley",
      "image_id": 21670
    },
    {
      "match": "freyaSub",
      "image_id": 21700
    },
    {
      "match": "freyaPizza",
      "image_id": 21703
    },
    {
      "match": "freyaSpoon",
      "image_id": 30187
    },
    {
      "match": "freyaShock",
      "image_id": 47553
    },
    {
      "match": "freyaKaffa",
      "image_id": 57000
    },
    {
      "match": "freyaCreep",
      "image_id": 58249
    }
  ]
}