{
  "name": "twitch-sub-godbokihs",
  "match": "word",
  "template": "<img src=\"//static-cdn.jtvnw.net/emoticons/v1/:image_id/1.0\" alt=\":match\" title=\":match\">",
  "icons": [
    {
      "match": "ppumePpu",
      "image_id": 67830
    },
    {
      "match": "ppumeYawn",
      "image_id": 67829
    },
    {
      "match": "ppumeSleep",
      "image_id": 69286
    },
    {
      "match": "ppumeBye",
      "image_id": 69285
    },
    {
      "match": "ppumePpume",
      "image_id": 67831
    },
    {
      "match": "ppumeNojam",
      "image_id": 90637
    }
  ]
}