{
  "name": "twitch-sub-jefmajor",
  "match": "word",
  "template": "<img src=\"//static-cdn.jtvnw.net/emoticons/v1/:image_id/1.0\" alt=\":match\" title=\":match\">",
  "icons": [
    {
      "match": "jspAc",
      "image_id": 60039
    },
    {
      "match": "jspMax",
      "image_id": 36754
    },
    {
      "match": "jspRage",
      "image_id": 36758
    },
    {
      "match": "jspValue",
      "image_id": 50941
    },
    {
      "match": "jspBvr",
      "image_id": 37073
    },
    {
      "match": "jspMemes",
      "image_id": 45790
    },
    {
      "match": "jspAirhorn",
      "image_id": 59903
    },
    {
      "match": "jspDerp",
      "image_id": 60124
    },
    {
      "match": "jspDwarf",
      "image_id": 76297
    }
  ]
}