{
  "name": "twitch-sub-kazimirtv",
  "match": "word",
  "template": "<img src=\"//static-cdn.jtvnw.net/emoticons/v1/:image_id/1.0\" alt=\":match\" title=\":match\">",
  "icons": [
    {
      "match": "kaziBR",
      "image_id": 6734
    },
    {
      "match": "kaziBD",
      "image_id": 6530
    },
    {
      "match": "kaziB",
      "image_id": 6529
    },
    {
      "match": "kaziDANKE",
      "image_id": 10871
    },
    {
      "match": "kaziFPALM",
      "image_id": 10872
    },
    {
      "match": "kaziEis",
      "image_id": 26650
    },
    {
      "match": "kaziHQG",
      "image_id": 28333
    },
    {
      "match": "kaziL2p",
      "image_id": 29015
    },
    {
      "match": "kaziGj",
      "image_id": 34587
    },
    {
      "match": "kaziHype",
      "image_id": 34612
    },
    {
      "match": "kaziArmy",
      "image_id": 37392
    },
    {
      "match": "kaziEasy",
      "image_id": 37393
    },
    {
      "match": "kaziRekt",
      "image_id": 37394
    },
    {
      "match": "kaziNga",
      "image_id": 37395
    },
    {
      "match": "kaziWth",
      "image_id": 37396
    }
  ]
}