{
  "name": "twitch-sub-krukz",
  "match": "word",
  "template": "<img src=\"//static-cdn.jtvnw.net/emoticons/v1/:image_id/1.0\" alt=\":match\" title=\":match\">",
  "icons": [
    {
      "match": "krukzTOB",
      "image_id": 51816
    },
    {
      "match": "krukzWAT",
      "image_id": 63026
    },
    {
      "match": "krukzPEAR",
      "image_id": 47230
    },
    {
      "match": "krukzRAGE",
      "image_id": 47698
    },
    {
      "match": "krukzKAPPA",
      "image_id": 47699
    },
    {
      "match": "krukzGG",
      "image_id": 47409
    },
    {
      "match": "krukzSCOUT",
      "image_id": 48478
    },
    {
      "match": "krukzTARD",
      "image_id": 60869
    },
    {
      "match": "krukzSUB",
      "image_id": 63025
    },
    {
      "match": "krukzJOO",
      "image_id": 70837
    }
  ]
}