{
  "name": "twitch-sub-lowkotv",
  "match": "word",
  "template": "<img src=\"//static-cdn.jtvnw.net/emoticons/v1/:image_id/1.0\" alt=\":match\" title=\":match\">",
  "icons": [
    {
      "match": "lowPalm",
      "image_id": 7800
    },
    {
      "match": "lowPa",
      "image_id": 7803
    },
    {
      "match": "lowGG",
      "image_id": 10764
    },
    {
      "match": "lowNO",
      "image_id": 10772
    },
    {
      "match": "lowVe",
      "image_id": 13676
    },
    {
      "match": "lowDerp",
      "image_id": 14314
    },
    {
      "match": "lowPOW",
      "image_id": 50910
    },
    {
      "match": "lowChair",
      "image_id": 63755
    },
    {
      "match": "lowHeart",
      "image_id": 64364
    },
    {
      "match": "lowCry",
      "image_id": 66211
    }
  ]
}