{
  "name": "twitch-sub-missharvey",
  "match": "word",
  "template": "<img src=\"//static-cdn.jtvnw.net/emoticons/v1/:image_id/1.0\" alt=\":match\" title=\":match\">",
  "icons": [
    {
      "match": "harveyPewR",
      "image_id": 33296
    },
    {
      "match": "harveyPewpew",
      "image_id": 33295
    },
    {
      "match": "harveyDeal",
      "image_id": 34527
    },
    {
      "match": "harveyTen",
      "image_id": 34526
    },
    {
      "match": "harveyUnsub",
      "image_id": 33171
    },
    {
      "match": "harveyFTV",
      "image_id": 33290
    },
    {
      "match": "harveyHAELP",
      "image_id": 33292
    },
    {
      "match": "harveyAce",
      "image_id": 33291
    },
    {
      "match": "harveyLove",
      "image_id": 33293
    },
    {
      "match": "harveyPew",
      "image_id": 33294
    },
    {
      "match": "harveyRage",
      "image_id": 33297
    },
    {
      "match": "harveyThrow",
      "image_id": 34716
    },
    {
      "match": "harveyCoq",
      "image_id": 34715
    },
    {
      "match": "harveyClutch",
      "image_id": 34714
    },
    {
      "match": "harveyGasm",
      "image_id": 34767
    }
  ]
}