{
  "name": "twitch-sub-mla626",
  "match": "word",
  "template": "<img src=\"//static-cdn.jtvnw.net/emoticons/v1/:image_id/1.0\" alt=\":match\" title=\":match\">",
  "icons": [
    {
      "match": "mlaKISS",
      "image_id": 38293
    },
    {
      "match": "mlaRAGE",
      "image_id": 40466
    },
    {
      "match": "mlaJUICE",
      "image_id": 40465
    },
    {
      "match": "mlaBACON",
      "image_id": 40463
    },
    {
      "match": "mlaDN",
      "image_id": 58768
    },
    {
      "match": "mlaBAN",
      "image_id": 58767
    }
  ]
}