{
  "name": "twitch-sub-ugarmy",
  "match": "word",
  "template": "<img src=\"//static-cdn.jtvnw.net/emoticons/v1/:image_id/1.0\" alt=\":match\" title=\":match\">",
  "icons": [
    {
      "match": "ugarmyYOLO",
      "image_id": 20703
    },
    {
      "match": "ugarmyCrew",
      "image_id": 18947
    },
    {
      "match": "ugarmyFist",
      "image_id": 20822
    },
    {
      "match": "ugarmyPumped",
      "image_id": 20908
    },
    {
      "match": "ugarmyBomb",
      "image_id": 20997
    },
    {
      "match": "ugarmyHype",
      "image_id": 20606
    }
  ]
}