{
  "name": "twitch-sub-yagamileong",
  "match": "word",
  "template": "<img src=\"//static-cdn.jtvnw.net/emoticons/v1/:image_id/1.0\" alt=\":match\" title=\":match\">",
  "icons": [
    {
      "match": "moyungHAND",
      "image_id": 40686
    },
    {
      "match": "moyungIcon1",
      "image_id": 22963
    },
    {
      "match": "moyungPoro",
      "image_id": 23932
    },
    {
      "match": "moyungCRY",
      "image_id": 40814
    },
    {
      "match": "moyungHA",
      "image_id": 40266
    },
    {
      "match": "moyungMOON",
      "image_id": 40358
    }
  ]
}