{
  "name": "twitch-sub-yoonie",
  "match": "word",
  "template": "<img src=\"//static-cdn.jtvnw.net/emoticons/v1/:image_id/1.0\" alt=\":match\" title=\":match\">",
  "icons": [
    {
      "match": "yoonSad",
      "image_id": 4819
    },
    {
      "match": "yoonWave",
      "image_id": 63561
    },
    {
      "match": "yoonLove",
      "image_id": 63560
    },
    {
      "match": "yoonCry",
      "image_id": 63559
    },
    {
      "match": "yoonFoot",
      "image_id": 8487
    },
    {
      "match": "yoonUguu",
      "image_id": 37079
    },
    {
      "match": "yoonGame",
      "image_id": 46980
    },
    {
      "match": "yoonSnack",
      "image_id": 50214
    }
  ]
}